deckling/__init__.py
deckling/cli.py
deckling/core.py
deckling/zipenhancer.py
deckling/model/__init__.py
deckling/model/utils.py
deckling/model/voxcpm.py
deckling/modules/__init__.py
deckling/modules/audiovae/__init__.py
deckling/modules/audiovae/audio_vae.py
deckling/modules/layers/__init__.py
deckling/modules/layers/scalar_quantization_layer.py
deckling/modules/locdit/__init__.py
deckling/modules/locdit/local_dit.py
deckling/modules/locdit/unified_cfm.py
deckling/modules/locenc/__init__.py
deckling/modules/locenc/local_encoder.py
deckling/modules/minicpm4/__init__.py
deckling/modules/minicpm4/cache.py
deckling/modules/minicpm4/config.py
deckling/modules/minicpm4/model.py
deckling/utils/text_normalize.py
deckling-0.0.4.dist-info/LICENSE
deckling-0.0.4.dist-info/WHEEL
deckling-0.0.4.dist-info/METADATA
deckling-0.0.4.dist-info/RECORD
