Metadata-Version: 2.1
Name: deckling
Version: 0.0.4
Summary: toolkit
Author-email: calcuis <info@calcu.io>
Classifier: License :: OSI Approved :: Apache Software License
Project-URL: Repository, https://github.com/calcuis/deckling
